CovarianceDescriptor/CovD.py
CovarianceDescriptor/__init__.py
Covariance_Descriptor-1.0.4.dist-info/LICENSE
Covariance_Descriptor-1.0.4.dist-info/METADATA
Covariance_Descriptor-1.0.4.dist-info/WHEEL
Covariance_Descriptor-1.0.4.dist-info/top_level.txt
Covariance_Descriptor-1.0.4.dist-info/RECORD
