Metadata-Version: 2.1
Name: Covariance-Descriptor
Version: 1.0.4
Summary: a image descriptor
Home-page: https://github.com/KongfeiH/Covariance-Descriptor
Author: Kongfei He
Author-email: hekongfei@outlook.com
License: UNKNOWN
Platform: UNKNOWN
Classifier: Programming Language :: Python :: 3
Classifier: License :: OSI Approved :: MIT License
Classifier: Operating System :: OS Independent
Requires-Python: >=3.6
Requires-Dist: numpy (>=1.16.2)
Requires-Dist: opencv-python (>=3.4.1)
Requires-Dist: scipy (>=1.4.1)
